{
	"textures":{"1":"block/fire_coral_block","2":"block/shrub_stem","3":"block/sweet_berry_bush","particle":"block/sweet_berry_bush"},
	"elements":[
		{
			"name":"Berry",
			"from":[6,13.25,7.75],
			"to":[7.5,14.75,9.25],
			"rotation":{"angle":0,"axis":"y","origin":[7,13.25,8]},
			"faces":{
				"north":{"uv":[4,0,6,2],"texture":"#1"},
				"east":{"uv":[4,4,6,6],"texture":"#1"},
				"south":{"uv":[4,4,6,6],"texture":"#1"},
				"west":{"uv":[4,0,6,2],"texture":"#1"},
				"up":{"uv":[4,2,6,4],"texture":"#1"},
				"down":{"uv":[4,2,6,4],"texture":"#1"}
			}
		},
		{
			"name":"Berry",
			"from":[13.25,8,8.75],
			"to":[14.75,9.5,10.25],
			"rotation":{"angle":0,"axis":"y","origin":[14.25,8,10]},
			"faces":{
				"north":{"uv":[2,2,4,4],"texture":"#1"},
				"east":{"uv":[2,2,4,4],"texture":"#1"},
				"south":{"uv":[2,2,4,4],"texture":"#1"},
				"west":{"uv":[2,2,4,4],"texture":"#1"},
				"up":{"uv":[2,0,4,2],"texture":"#1"},
				"down":{"uv":[2,4,4,6],"texture":"#1"}
			}
		},
		{
			"name":"Berry",
			"from":[13,11,4.75],
			"to":[14.5,12.5,6.25],
			"rotation":{"angle":0,"axis":"y","origin":[13,12,5]},
			"faces":{
				"north":{"uv":[0,2,2,4],"texture":"#1"},
				"east":{"uv":[0,2,2,4],"texture":"#1"},
				"south":{"uv":[0,2,2,4],"texture":"#1"},
				"west":{"uv":[0,2,2,4],"texture":"#1"},
				"up":{"uv":[0,0,2,2],"texture":"#1"},
				"down":{"uv":[0,4,2,6],"texture":"#1"}
			}
		},
		{
			"name":"Berry",
			"from":[5,9,12.75],
			"to":[6.5,10.5,14.25],
			"rotation":{"angle":0,"axis":"y","origin":[6,10,13]},
			"faces":{
				"north":{"uv":[0,2,2,4],"texture":"#1"},
				"east":{"uv":[0,2,2,4],"texture":"#1"},
				"south":{"uv":[0,2,2,4],"texture":"#1"},
				"west":{"uv":[0,2,2,4],"texture":"#1"},
				"up":{"uv":[0,0,2,2],"texture":"#1"},
				"down":{"uv":[0,4,2,6],"texture":"#1"}
			}
		},
		{
			"name":"Berry",
			"from":[3,11,4.75],
			"to":[4.5,12.5,6.25],
			"rotation":{"angle":0,"axis":"y","origin":[4,12,6]},
			"faces":{
				"north":{"uv":[2,2,4,4],"texture":"#1"},
				"east":{"uv":[2,2,4,4],"texture":"#1"},
				"south":{"uv":[2,2,4,4],"texture":"#1"},
				"west":{"uv":[2,2,4,4],"texture":"#1"},
				"up":{"uv":[2,0,4,2],"texture":"#1"},
				"down":{"uv":[2,4,4,6],"texture":"#1"}
			}
		},
		{
			"name":"Berry",
			"from":[7,8,1.5],
			"to":[8.5,9.5,3],
			"rotation":{"angle":0,"axis":"y","origin":[7,8,2.75]},
			"faces":{
				"north":{"uv":[0,2,2,4],"texture":"#1"},
				"east":{"uv":[0,2,2,4],"texture":"#1"},
				"south":{"uv":[0,2,2,4],"texture":"#1"},
				"west":{"uv":[0,2,2,4],"texture":"#1"},
				"up":{"uv":[0,0,2,2],"texture":"#1"},
				"down":{"uv":[0,4,2,6],"texture":"#1"}
			}
		},
		{
			"name":"Stem",
			"from":[0.8,0,8],
			"to":[15.2,16,8],
			"shade":false,
			"rotation":{"angle":45,"axis":"y","origin":[8,8,8],"rescale":true},
			"faces":{
				"north":{"uv":[0,0,16,16],"texture":"#2"},
				"south":{"uv":[0,0,16,16],"texture":"#2"}
			}
		},
		{
			"name":"Stem",
			"from":[8,0,0.8],
			"to":[8,16,15.2],
			"shade":false,
			"rotation":{"angle":45,"axis":"y","origin":[8,8,8],"rescale":true},
			"faces":{
				"east":{"uv":[0,0,16,16],"texture":"#2"},
				"west":{"uv":[0,0,16,16],"texture":"#2"}
			}
		},
		{
			"name":"Leaves Middle1",
			"from":[2,5,14],
			"to":[14,15,14],
			"shade":false,
			"rotation":{"angle":-22.5,"axis":"x","origin":[8,8,14],"rescale":true},
			"faces":{
				"north":{"uv":[0,0,16,16],"texture":"#3","tintindex":0},
				"south":{"uv":[0,0,16,16],"texture":"#3","tintindex":0}
			}
		},
		{
			"name":"Leaves Middle2",
			"from":[2,5,2],
			"to":[14,15,2],
			"shade":false,
			"rotation":{"angle":22.5,"axis":"x","origin":[8,8,2],"rescale":true},
			"faces":{
				"north":{"uv":[0,0,16,16],"texture":"#3","tintindex":0},
				"south":{"uv":[0,0,16,16],"texture":"#3","tintindex":0}
			}
		},
		{
			"name":"Leaves Middle2",
			"from":[2,5,2],
			"to":[2,15,14],
			"shade":false,
			"rotation":{"angle":-22.5,"axis":"z","origin":[2,8,8],"rescale":true},
			"faces":{
				"east":{"uv":[0,0,16,16],"texture":"#3","tintindex":0},
				"west":{"uv":[0,0,16,16],"texture":"#3","tintindex":0}
			}
		},
		{
			"name":"Leaves Middle1",
			"from":[14,5,2],
			"to":[14,15,14],
			"shade":false,
			"rotation":{"angle":22.5,"axis":"z","origin":[14,8,8],"rescale":true},
			"faces":{
				"east":{"uv":[0,0,16,16],"texture":"#3","tintindex":0},
				"west":{"uv":[0,0,16,16],"texture":"#3","tintindex":0}
			}
		},
		{
			"name":"Leaves Top4",
			"from":[2,14,0],
			"to":[14,14,10],
			"shade":false,
			"rotation":{"angle":-22.5,"axis":"x","origin":[8,14,8],"rescale":true},
			"faces":{
				"up":{"uv":[0,0,16,16],"texture":"#3","tintindex":0},
				"down":{"uv":[0,0,16,16],"texture":"#3","tintindex":0}
			}
		},
		{
			"name":"Leaves Top3",
			"from":[2,14,6],
			"to":[14,14,16],
			"shade":false,
			"rotation":{"angle":22.5,"axis":"x","origin":[8,14,8],"rescale":true},
			"faces":{
				"up":{"uv":[0,0,16,16],"texture":"#3","tintindex":0},
				"down":{"uv":[0,0,16,16],"texture":"#3","tintindex":0}
			}
		},
		{
			"name":"Leaves Top2",
			"from":[0,14,2],
			"to":[10,14,14],
			"shade":false,
			"rotation":{"angle":22.5,"axis":"z","origin":[8,14,8],"rescale":true},
			"faces":{
				"up":{"uv":[0,0,16,16],"texture":"#3","tintindex":0},
				"down":{"uv":[0,0,16,16],"texture":"#3","tintindex":0}
			}
		},
		{
			"name":"Leaves Top1",
			"from":[6,14,2],
			"to":[16,14,14],
			"shade":false,
			"rotation":{"angle":-22.5,"axis":"z","origin":[8,14,8],"rescale":true},
			"faces":{
				"up":{"uv":[0,0,16,16],"texture":"#3","tintindex":0},
				"down":{"uv":[0,0,16,16],"texture":"#3","tintindex":0}
			}
		}
	],
	"groups":[
		{"name":"berry","origin":[7,5,3],"color":0,"children":[0,1,2,3,4,5]},
		{"name":"shrub","origin":[8,14,8],"color":0,"children":[6,7,8,9,10,11,12,13,14,15]}
	]
}
